griptape_nodes/__init__.py
griptape_nodes/__main__.py
griptape_nodes/api_client/__init__.py
griptape_nodes/api_client/client.py
griptape_nodes/api_client/request_client.py
griptape_nodes/app/.python-version
griptape_nodes/app/__init__.py
griptape_nodes/app/app.py
griptape_nodes/app/watch.py
griptape_nodes/bootstrap/__init__.py
griptape_nodes/bootstrap/utils/__init__.py
griptape_nodes/bootstrap/utils/python_subprocess_executor.py
griptape_nodes/bootstrap/workflow_executors/__init__.py
griptape_nodes/bootstrap/workflow_executors/local_session_workflow_executor.py
griptape_nodes/bootstrap/workflow_executors/local_workflow_executor.py
griptape_nodes/bootstrap/workflow_executors/subprocess_workflow_executor.py
griptape_nodes/bootstrap/workflow_executors/utils/__init__.py
griptape_nodes/bootstrap/workflow_executors/utils/subprocess_script.py
griptape_nodes/bootstrap/workflow_executors/workflow_executor.py
griptape_nodes/bootstrap/workflow_publishers/__init__.py
griptape_nodes/bootstrap/workflow_publishers/local_workflow_publisher.py
griptape_nodes/bootstrap/workflow_publishers/subprocess_workflow_publisher.py
griptape_nodes/bootstrap/workflow_publishers/utils/__init__.py
griptape_nodes/bootstrap/workflow_publishers/utils/subprocess_script.py
griptape_nodes/cli/__init__.py
griptape_nodes/cli/commands/__init__.py
griptape_nodes/cli/commands/config.py
griptape_nodes/cli/commands/engine.py
griptape_nodes/cli/commands/init.py
griptape_nodes/cli/commands/libraries.py
griptape_nodes/cli/commands/models.py
griptape_nodes/cli/commands/self.py
griptape_nodes/cli/main.py
griptape_nodes/cli/shared.py
griptape_nodes/common/__init__.py
griptape_nodes/common/directed_graph.py
griptape_nodes/common/macro_parser/__init__.py
griptape_nodes/common/macro_parser/core.py
griptape_nodes/common/macro_parser/exceptions.py
griptape_nodes/common/macro_parser/formats.py
griptape_nodes/common/macro_parser/matching.py
griptape_nodes/common/macro_parser/parsing.py
griptape_nodes-0.66.2.dist-info/WHEEL
griptape_nodes-0.66.2.dist-info/entry_points.txt
griptape_nodes-0.66.2.dist-info/METADATA
griptape_nodes-0.66.2.dist-info/RECORD
