Metadata-Version: 2.3
Name: griptape-nodes
Version: 0.66.2
Summary: Add your description here
Requires-Dist: griptape>=1.8.12
Requires-Dist: pydantic>=2.10.6
Requires-Dist: python-dotenv>=1.0.1
Requires-Dist: xdg-base-dirs>=6.0.2
Requires-Dist: httpx>=0.28.0,<1.0.0
Requires-Dist: websockets>=15.0.1,<16.0.0
Requires-Dist: tomlkit>=0.13.2
Requires-Dist: uv>=0.6.16
Requires-Dist: fastapi>=0.115.12
Requires-Dist: uvicorn>=0.34.2
Requires-Dist: packaging>=25.0
Requires-Dist: python-multipart>=0.0.20
Requires-Dist: json-repair>=0.46.1
Requires-Dist: mcp[ws]>=1.10.1
Requires-Dist: binaryornot>=0.4.4
Requires-Dist: pillow>=11.3.0
Requires-Dist: watchfiles>=1.1.0
Requires-Dist: typer>=0.15.0
Requires-Dist: huggingface-hub>=1.1.0
Requires-Dist: rich>=14.1.0
Requires-Dist: semver>=3.0.4
Requires-Dist: aiofiles>=25.1.0
Requires-Dist: aioshutil>=1.5
Requires-Dist: ruamel-yaml>=0.18.15
Requires-Dist: asyncio-thread-runner>=1.0
Requires-Dist: portalocker>=2.10.0
Requires-Dist: pygit2>=1.19.0
Requires-Dist: austin-dist>=3.7.0 ; extra == 'profiling'
Requires-Python: >=3.12.0, <3.13
Provides-Extra: profiling
